docs/source/conf.py
jax_privacy/__init__.py
jax_privacy/accounting/__init__.py
jax_privacy/accounting/accountants.py
jax_privacy/accounting/analysis.py
jax_privacy/accounting/analysis_test.py
jax_privacy/accounting/calibrate.py
jax_privacy/accounting/calibrate_test.py
jax_privacy/auditing/__init__.py
jax_privacy/auditing/canary_score_auditor.py
jax_privacy/auditing/canary_score_auditor_test.py
jax_privacy/dp_sgd/__init__.py
jax_privacy/dp_sgd/grad_clipping.py
jax_privacy/dp_sgd/grad_clipping_sharded_test.py
jax_privacy/dp_sgd/grad_clipping_test.py
jax_privacy/dp_sgd/grad_clipping_utils.py
jax_privacy/dp_sgd/gradients.py
jax_privacy/dp_sgd/gradients_test.py
jax_privacy/dp_sgd/metrics_accumulator.py
jax_privacy/dp_sgd/optim.py
jax_privacy/dp_sgd/optim_test.py
jax_privacy/dp_sgd/typing.py
jax_privacy/dp_sgd/wrapped_privatizer.py
jax_privacy/experimental/__init__.py
jax_privacy/experimental/batch_selection.py
jax_privacy/experimental/batch_selection_test.py
jax_privacy/experimental/clipping.py
jax_privacy/experimental/clipping_test.py
jax_privacy/experimental/execution_plan.py
jax_privacy/experimental/execution_plan_test.py
jax_privacy/experimental/gradient_clipping.py
jax_privacy/experimental/gradient_clipping_test.py
jax_privacy/experimental/microbatching.py
jax_privacy/experimental/microbatching_test.py
jax_privacy/keras/__init__.py
jax_privacy/keras/keras_api.py
jax_privacy/keras/keras_api_test.py
jax_privacy/matrix_factorization/__init__.py
jax_privacy/matrix_factorization/banded.py
jax_privacy/matrix_factorization/banded_test.py
jax_privacy/matrix_factorization/buffered_toeplitz.py
jax_privacy/matrix_factorization/buffered_toeplitz_test.py
jax_privacy/matrix_factorization/checks.py
jax_privacy/matrix_factorization/checks_test.py
jax_privacy/matrix_factorization/dense.py
jax_privacy/matrix_factorization/dense_test.py
jax_privacy/matrix_factorization/optimization.py
jax_privacy/matrix_factorization/optimization_test.py
jax_privacy-1.0.0.dist-info/licenses/LICENSE
jax_privacy-1.0.0.dist-info/METADATA
jax_privacy-1.0.0.dist-info/WHEEL
jax_privacy-1.0.0.dist-info/top_level.txt
jax_privacy-1.0.0.dist-info/RECORD
