Metadata-Version: 2.4
Name: jax_privacy
Version: 1.0.0
Summary: Algorithms for Privacy-Preserving Machine Learning in JAX.
Home-page: https://github.com/google-deepmind/jax_privacy
Author: Google DeepMind
Author-email: jax-privacy-dev@google.com
License: Apache 2.0
Platform: any
License-File: LICENSE
Requires-Dist: absl-py
Requires-Dist: dp_accounting
Requires-Dist: einshape
Requires-Dist: grain
Requires-Dist: hypothesis
Requires-Dist: jax==0.6.2
Requires-Dist: jaxlib==0.6.2
Requires-Dist: jaxtyping
Requires-Dist: pydantic
Requires-Dist: ml_collections
Requires-Dist: more_itertools==10.1.0
Requires-Dist: numpy
Requires-Dist: optax
Requires-Dist: scipy
Dynamic: author
Dynamic: author-email
Dynamic: home-page
Dynamic: license
Dynamic: license-file
Dynamic: platform
Dynamic: requires-dist
Dynamic: summary
